dir_tree_printer/__init__.py
dir_tree_printer/cli.py
dir_tree_printer/core.py
dir_tree_printer-0.1.1.dist-info/METADATA
dir_tree_printer-0.1.1.dist-info/WHEEL
dir_tree_printer-0.1.1.dist-info/entry_points.txt
dir_tree_printer-0.1.1.dist-info/licenses/LICENSE
dir_tree_printer-0.1.1.dist-info/RECORD
