Metadata-Version: 2.4
Name: dir-tree-printer
Version: 0.1.1
Summary: A simple utility to print directory structures in a tree-like format
Project-URL: Homepage, https://github.com/NAGARAJ08/tree-printer
Author-email: Nagaraj K <kbnagaraj18@gmail.com>
License: MIT License
License-File: LICENSE
Keywords: directory,structure,tree,visualization
Classifier: License :: OSI Approved :: MIT License
Classifier: Programming Language :: Python
Classifier: Programming Language :: Python :: 3
Requires-Python: >=3.7
